binned_cdf/__init__.py
binned_cdf/binned_logit_cdf.py
binned_cdf-1.0.1.dist-info/METADATA
binned_cdf-1.0.1.dist-info/WHEEL
binned_cdf-1.0.1.dist-info/RECORD
