Metadata-Version: 2.4
Name: binned-cdf
Version: 1.0.1
Summary: A PyTorch-based distribution parametrized by the logits of CDF bins
Project-URL: homepage, https://famura.github.io/binned-cdf
Project-URL: source, https://github.com/famura/binned-cdf
Author-email: Fabio Muratore <accounts@famura.net>
Maintainer-email: Fabio Muratore <accounts@famura.net>
License-Expression: CC-BY-4.0
Classifier: Development Status :: 3 - Alpha
Classifier: Intended Audience :: Science/Research
Classifier: Natural Language :: English
Classifier: Programming Language :: Python :: 3.11
Classifier: Programming Language :: Python :: 3.12
Classifier: Programming Language :: Python :: 3.13
Classifier: Topic :: Scientific/Engineering
Requires-Python: >=3.11
Requires-Dist: torch>=2.7
Provides-Extra: examples
Requires-Dist: scikit-learn>=1.7.2; extra == 'examples'
